{
  "id": "RepoMount",
  "name": "RepoMount",
  "parentId": "Item",
  "preventModification": true,
  "restrictInstanceEditing": true,
  "namespace": {
    "id": "com.kohese.metamodel"
  },
  "base": "Item",
  "idInjection": true,
  "invertItemOrder": true,
  "properties": {
    "mountPoint": {
      "name": "mountPoint",
      "type": "Item",
      "required": true,
      "relation": {
        "kind": "Item",
        "foreignKey": "id"
      }
    },
    "repoId": {
      "name": "repoId",
      "type": "Repository",
      "required": true,
      "relation": {
        "kind": "Item",
        "foreignKey": "id"
      }
    }
  },
  "validations": [],
  "relations": {},
  "acls": [],
  "methods": [],
  "localTypes": {}
}
